nerfacc/__init__.py
nerfacc/cameras.py
nerfacc/data_specs.py
nerfacc/grid.py
nerfacc/pack.py
nerfacc/pdf.py
nerfacc/scan.py
nerfacc/version.py
nerfacc/volrend.py
nerfacc/cuda/__init__.py
nerfacc/cuda/_backend.py
nerfacc/cuda/csrc/camera.cu
nerfacc/cuda/csrc/grid.cu
nerfacc/cuda/csrc/nerfacc.cpp
nerfacc/cuda/csrc/pdf.cu
nerfacc/cuda/csrc/scan.cu
nerfacc/cuda/csrc/include/data_spec.hpp
nerfacc/cuda/csrc/include/data_spec_packed.cuh
nerfacc/cuda/csrc/include/utils_camera.cuh
nerfacc/cuda/csrc/include/utils_contraction.cuh
nerfacc/cuda/csrc/include/utils_cuda.cuh
nerfacc/cuda/csrc/include/utils_grid.cuh
nerfacc/cuda/csrc/include/utils_math.cuh
nerfacc/cuda/csrc/include/utils_scan.cuh
nerfacc/estimators/__init__.py
nerfacc/estimators/base.py
nerfacc/estimators/occ_grid.py
nerfacc/estimators/prop_net.py
nerfacc-0.5.3.dist-info/LICENSE
nerfacc-0.5.3.dist-info/METADATA
nerfacc-0.5.3.dist-info/WHEEL
nerfacc-0.5.3.dist-info/top_level.txt
nerfacc-0.5.3.dist-info/RECORD
