Metadata-Version: 2.1
Name: nerfacc
Version: 0.5.3
Summary: A General NeRF Acceleration Toolbox
Home-page: https://github.com/KAIR-BAIR/nerfacc
Download-URL: https://github.com/KAIR-BAIR/nerfacc/archive/0.5.3.tar.gz
Author: Ruilong
Author-email: ruilongli94@gmail.com
Requires-Python: >=3.7
License-File: LICENSE
Requires-Dist: rich (>=12)
Requires-Dist: torch
Requires-Dist: typing-extensions ; python_version < "3.8"
Provides-Extra: dev
Requires-Dist: black[jupyter] (==22.3.0) ; extra == 'dev'
Requires-Dist: isort (==5.10.1) ; extra == 'dev'
Requires-Dist: pylint (==2.13.4) ; extra == 'dev'
Requires-Dist: pytest (==7.1.2) ; extra == 'dev'
Requires-Dist: pytest-xdist (==2.5.0) ; extra == 'dev'
Requires-Dist: typeguard (>=2.13.3) ; extra == 'dev'
Requires-Dist: pyyaml (==6.0) ; extra == 'dev'
Requires-Dist: build ; extra == 'dev'
Requires-Dist: twine ; extra == 'dev'
Requires-Dist: ninja ; extra == 'dev'
